pyfuze/__init__.py
pyfuze/__main__.py
pyfuze/cli.py
pyfuze/pyfuze.com
pyfuze/python.com
pyfuze/utils.py
pyfuze-2.7.2.dist-info/WHEEL
pyfuze-2.7.2.dist-info/entry_points.txt
pyfuze-2.7.2.dist-info/METADATA
pyfuze-2.7.2.dist-info/RECORD
