Metadata-Version: 2.3
Name: pyfuze
Version: 2.7.2
Summary: Package Python projects into executables
Author: Tanix
Author-email: Tanix <tanixlu@foxmail.com>
License: MIT
Requires-Dist: click>=8.1.8
Requires-Python: >=3.8
